[{"_id":"5bf478978529e15368205516","pd_appointment_uuid":"ef987691-0a19-447f-814d-f8f3abbf4859","appointment_id":"SNBFZKCYTPDT","appointment_type":"OV1","patient":{"first_name":"John","last_name":"Doe","_uuid":"8b21f7b0-8535-11e4-a6cb-0800272e8da1","phone":"800-555-1212","member_id":"M000001","birth_date":"1970-01-25","email":"john@johndoe.com"},"status":"booked","provider_scheduler_uuid":"8b21efa4-8535-11e4-a6cb-0800272e8da1","start_date":"2018-11-21T16:30:00.000Z","end_date":"2018-11-21T17:00:00.000Z","_acl":{"creator":"5bb4c957d16a1c1c79edbf00"},"_kmd":{"lmt":"2018-11-20T21:11:51.460Z","ect":"2018-11-20T21:11:51.460Z"}},{"_id":"5c0f7a963560971f17797ac6","pd_appointment_uuid":"ef987691-0a19-447f-814d-f8f3abbf4859","appointment_id":"QYCLCPKOJEQA","appointment_type":"OV1","patient":{"first_name":"John","last_name":"Doe","_uuid":"8b21f7b0-8535-11e4-a6cb-0800272e8da1","phone":"800-555-1212","member_id":"M000001","birth_date":"1970-01-25","email":"john@johndoe.com"},"status":"booked","provider_scheduler_uuid":"8b21efa4-8535-11e4-a6cb-0800272e8da1","start_date":"2018-12-12T04:00:00.000Z","end_date":"2018-12-12T04:30:00.000Z","_acl":{"creator":"5bb6e21da6e95245bc3cfa74"},"_kmd":{"lmt":"2018-12-11T08:51:34.212Z","ect":"2018-12-11T08:51:34.212Z"}}]